{
  "characterId": "ed",
  "displayNameCN": "",
  "displayNameEN": "Ed",
  "lastUpdated": "2026-01-31",
  "columns": [
    "id",
    "category",
    "nameEN",
    "nameCN",
    "input",
    "inputDisplay",
    "hitType",
    "startup",
    "active",
    "recovery",
    "onBlock",
    "onHit",
    "damage",
    "superArt",
    "driveOnHit",
    "driveOnBlock",
    "driveOnPunishCounter",
    "cancel"
  ],
  "nameCNMap": {
    "st_lp": "站轻拳",
    "st_mp": "站中拳",
    "st_hp": "站重拳",
    "st_lk": "站轻脚",
    "st_mk": "站中脚",
    "st_hk": "站重脚",
    "cr_lp": "下轻拳",
    "cr_mp": "下中拳",
    "cr_hp": "下重拳",
    "cr_lk": "下轻脚",
    "cr_mk": "下中脚",
    "cr_hk": "下重脚",
    "j_lp": "跳轻拳",
    "j_mp": "跳中拳",
    "j_hp": "跳重拳",
    "j_lk": "跳轻脚",
    "j_mk": "跳中脚",
    "j_hk": "跳重脚",
    "psycho_knuckle_charged_level_1": "サイコナックル（ホールド Lv1）",
    "psycho_knuckle_charged_level_2": "サイコナックル（ホールド Lv2）",
    "f_hp": "サイコシュート（OD 強）",
    "flicker_combination_2": "フリッカーコンビネーション（2段目）",
    "flicker_combination_3": "フリッカーコンビネーション（3段目）",
    "body_blow_combination": "ボディブローコンビネーション",
    "hitman_combination_2": "ヒットマンコンビネーション（2段目）",
    "hitman_combination_3": "ヒットマンコンビネーション（3段目）",
    "low_smash_combination": "ロースマッシュコンビネーション",
    "psycho_spark": "サイコスパーク",
    "psycho_spark_od": "サイコスパーク（OD）",
    "f_lp": "サイコシュート（OD 弱）",
    "f_mp": "サイコシュート（OD 中）",
    "psycho_uppercut_light": "サイコアッパー（弱）",
    "psycho_uppercut_medium": "サイコアッパー（中）",
    "psycho_uppercut_heavy": "サイコアッパー（強）",
    "psycho_uppercut_od": "サイコアッパー（OD）",
    "psycho_blitz_light": "サイコブリッツ（弱）",
    "psycho_blitz_medium": "サイコブリッツ（中）",
    "psycho_blitz_heavy": "サイコブリッツ（強）",
    "psycho_blitz_od": "サイコブリッツ（OD）",
    "psycho_flicker_light": "サイコフリッカー（弱）",
    "psycho_flicker_light_charged": "サイコフリッカー（弱 ホールド）",
    "psycho_flicker_medium": "サイコフリッカー（中）",
    "psycho_flicker_medium_charged": "サイコフリッカー（中 ホールド）",
    "psycho_flicker_heavy": "サイコフリッカー（強）",
    "psycho_flicker_heavy_charged": "サイコフリッカー（強 ホールド）",
    "psycho_flicker_od": "サイコフリッカー（OD）",
    "kill_rush_forward": "キルステップ（前方）",
    "kill_switch_break": "キルスイッチ・ブレイク",
    "kill_switch_chaser": "キルスイッチ・チェイス",
    "kill_rush_backward": "キルステップ（後方）",
    "psycho_storm": "サイコストーム",
    "psycho_cannon": "サイコキャノン",
    "psycho_chamber": "サイコチェンバー",
    "psycho_chamber_critical_art": "サイコチェンバー（CA）",
    "face_buster": "フェイスバスター",
    "rib_crusher": "リブクラッシャー"
  },
  "moves": [
    {
      "id": "st_lp",
      "category": "normal",
      "nameEN": "Standing Light Punch",
      "nameCN": "站轻拳",
      "input": "5lp",
      "inputDisplay": "",
      "hitType": "High",
      "startup": "4",
      "active": "3",
      "recovery": "7",
      "onBlock": "-1",
      "onHit": "4",
      "damage": "300",
      "superArt": "300",
      "driveOnHit": "250",
      "driveOnBlock": "-500",
      "driveOnPunishCounter": "-2000",
      "cancel": "Special, Drive, Super"
    },
    {
      "id": "st_mp",
      "category": "normal",
      "nameEN": "Standing Medium Punch",
      "nameCN": "站中拳",
      "input": "5mp",
      "inputDisplay": "",
      "hitType": "High",
      "startup": "7",
      "active": "3",
      "recovery": "15",
      "onBlock": "-1",
      "onHit": "6",
      "damage": "600",
      "superArt": "500",
      "driveOnHit": "1500",
      "driveOnBlock": "-3000",
      "driveOnPunishCounter": "-4000",
      "cancel": "Special, Drive, Super"
    },
    {
      "id": "st_hp",
      "category": "normal",
      "nameEN": "Standing Heavy Punch",
      "nameCN": "站重拳",
      "input": "5hp",
      "inputDisplay": "",
      "hitType": "High",
      "startup": "10",
      "active": "4",
      "recovery": "18",
      "onBlock": "-2",
      "onHit": "5",
      "damage": "800",
      "superArt": "1000",
      "driveOnHit": "2000",
      "driveOnBlock": "-5000",
      "driveOnPunishCounter": "-8000",
      "cancel": "Special, Drive, Super"
    },
    {
      "id": "st_lk",
      "category": "normal",
      "nameEN": "Standing Light Kick",
      "nameCN": "站轻脚",
      "input": "5lk",
      "inputDisplay": "",
      "hitType": "Low",
      "startup": "6",
      "active": "2",
      "recovery": "13",
      "onBlock": "-3",
      "onHit": "3",
      "damage": "300",
      "superArt": "300",
      "driveOnHit": "250",
      "driveOnBlock": "-500",
      "driveOnPunishCounter": "-2000",
      "cancel": "-"
    },
    {
      "id": "st_mk",
      "category": "normal",
      "nameEN": "Standing Medium Kick",
      "nameCN": "站中脚",
      "input": "5mk",
      "inputDisplay": "",
      "hitType": "Low",
      "startup": "10",
      "active": "2",
      "recovery": "18",
      "onBlock": "-5",
      "onHit": "0",
      "damage": "600",
      "superArt": "700",
      "driveOnHit": "1500",
      "driveOnBlock": "-3000",
      "driveOnPunishCounter": "-4000",
      "cancel": "Special, Drive, Super"
    },
    {
      "id": "st_hk",
      "category": "normal",
      "nameEN": "Standing Heavy Kick",
      "nameCN": "站重脚",
      "input": "5hk",
      "inputDisplay": "",
      "hitType": "Low",
      "startup": "10",
      "active": "3",
      "recovery": "12",
      "onBlock": "4",
      "onHit": "8",
      "damage": "800",
      "superArt": "1000",
      "driveOnHit": "3000",
      "driveOnBlock": "-6000",
      "driveOnPunishCounter": "-10000",
      "cancel": "Special, Drive, Super"
    },
    {
      "id": "cr_lp",
      "category": "normal",
      "nameEN": "Crouching Light Punch",
      "nameCN": "下轻拳",
      "input": "2lp",
      "inputDisplay": "",
      "hitType": "Low",
      "startup": "4",
      "active": "3",
      "recovery": "10",
      "onBlock": "-3",
      "onHit": "3",
      "damage": "200",
      "superArt": "300",
      "driveOnHit": "250",
      "driveOnBlock": "-500",
      "driveOnPunishCounter": "-2000",
      "cancel": "-"
    },
    {
      "id": "cr_mp",
      "category": "normal",
      "nameEN": "Crouching Medium Punch",
      "nameCN": "下中拳",
      "input": "2mp",
      "inputDisplay": "",
      "hitType": "Low",
      "startup": "8",
      "active": "3",
      "recovery": "19",
      "onBlock": "-6",
      "onHit": "2",
      "damage": "500",
      "superArt": "500",
      "driveOnHit": "1000",
      "driveOnBlock": "-2000",
      "driveOnPunishCounter": "-4000",
      "cancel": "Special, Drive, Super"
    },
    {
      "id": "cr_hp",
      "category": "normal",
      "nameEN": "Crouching Heavy Punch",
      "nameCN": "下重拳",
      "input": "2hp",
      "inputDisplay": "",
      "hitType": "Low",
      "startup": "10",
      "active": "4",
      "recovery": "24",
      "onBlock": "-12",
      "onHit": "-",
      "damage": "900",
      "superArt": "1000",
      "driveOnHit": "3000",
      "driveOnBlock": "-4000",
      "driveOnPunishCounter": "-10000",
      "cancel": "-"
    },
    {
      "id": "cr_lk",
      "category": "normal",
      "nameEN": "Crouching Light Kick",
      "nameCN": "下轻脚",
      "input": "2lk",
      "inputDisplay": "",
      "hitType": "High",
      "startup": "5",
      "active": "2",
      "recovery": "11",
      "onBlock": "-4",
      "onHit": "3",
      "damage": "300",
      "superArt": "300",
      "driveOnHit": "250",
      "driveOnBlock": "-500",
      "driveOnPunishCounter": "-2000",
      "cancel": "Special, Drive, Super"
    },
    {
      "id": "cr_mk",
      "category": "normal",
      "nameEN": "Crouching Medium Kick",
      "nameCN": "下中脚",
      "input": "2mk",
      "inputDisplay": "",
      "hitType": "High",
      "startup": "9",
      "active": "2",
      "recovery": "16",
      "onBlock": "-1",
      "onHit": "8",
      "damage": "600",
      "superArt": "600",
      "driveOnHit": "1500",
      "driveOnBlock": "-3000",
      "driveOnPunishCounter": "-4000",
      "cancel": "Special, Drive, Super"
    },
    {
      "id": "cr_hk",
      "category": "normal",
      "nameEN": "Crouching Heavy Kick",
      "nameCN": "下重脚",
      "input": "2hk",
      "inputDisplay": "",
      "hitType": "High",
      "startup": "12",
      "active": "2",
      "recovery": "17",
      "onBlock": "-4",
      "onHit": "1",
      "damage": "800",
      "superArt": "1000",
      "driveOnHit": "2000",
      "driveOnBlock": "-4000",
      "driveOnPunishCounter": "-8000",
      "cancel": "Special, Drive, Super"
    },
    {
      "id": "j_lp",
      "category": "normal",
      "nameEN": "Jumping Light Punch",
      "nameCN": "跳轻拳",
      "input": "j>lp",
      "inputDisplay": "",
      "hitType": "Overhead",
      "startup": "5",
      "active": "5",
      "recovery": "-",
      "onBlock": "-",
      "onHit": "-",
      "damage": "300",
      "superArt": "300",
      "driveOnHit": "500",
      "driveOnBlock": "-1500",
      "driveOnPunishCounter": "-2000",
      "cancel": "-"
    },
    {
      "id": "j_mp",
      "category": "normal",
      "nameEN": "Jumping Medium Punch",
      "nameCN": "跳中拳",
      "input": "j>mp",
      "inputDisplay": "",
      "hitType": "Overhead",
      "startup": "8",
      "active": "6",
      "recovery": "-",
      "onBlock": "-",
      "onHit": "-",
      "damage": "500",
      "superArt": "500",
      "driveOnHit": "1000",
      "driveOnBlock": "-2500",
      "driveOnPunishCounter": "-4000",
      "cancel": "-"
    },
    {
      "id": "j_hp",
      "category": "normal",
      "nameEN": "Jumping Heavy Punch",
      "nameCN": "跳重拳",
      "input": "j>hp",
      "inputDisplay": "",
      "hitType": "Overhead",
      "startup": "9",
      "active": "5",
      "recovery": "-",
      "onBlock": "-",
      "onHit": "-",
      "damage": "800",
      "superArt": "1000",
      "driveOnHit": "2000",
      "driveOnBlock": "-4000",
      "driveOnPunishCounter": "-5000",
      "cancel": "-"
    },
    {
      "id": "j_lk",
      "category": "normal",
      "nameEN": "Jumping Light Kick",
      "nameCN": "跳轻脚",
      "input": "j>lk",
      "inputDisplay": "",
      "hitType": "Overhead",
      "startup": "8",
      "active": "3",
      "recovery": "-",
      "onBlock": "-",
      "onHit": "-",
      "damage": "300",
      "superArt": "300",
      "driveOnHit": "500",
      "driveOnBlock": "-1500",
      "driveOnPunishCounter": "-2000",
      "cancel": "-"
    },
    {
      "id": "j_mk",
      "category": "normal",
      "nameEN": "Jumping Medium Kick",
      "nameCN": "跳中脚",
      "input": "j>mk",
      "inputDisplay": "",
      "hitType": "Overhead",
      "startup": "10",
      "active": "2",
      "recovery": "-",
      "onBlock": "-",
      "onHit": "-",
      "damage": "700",
      "superArt": "500",
      "driveOnHit": "1000",
      "driveOnBlock": "-3000",
      "driveOnPunishCounter": "-4000",
      "cancel": "-"
    },
    {
      "id": "j_hk",
      "category": "normal",
      "nameEN": "Jumping Heavy Kick",
      "nameCN": "跳重脚",
      "input": "j>hk",
      "inputDisplay": "",
      "hitType": "Overhead",
      "startup": "8",
      "active": "2",
      "recovery": "-",
      "onBlock": "-",
      "onHit": "-",
      "damage": "800",
      "superArt": "1000",
      "driveOnHit": "2000",
      "driveOnBlock": "-4000",
      "driveOnPunishCounter": "-5000",
      "cancel": "-"
    },
    {
      "id": "psycho_knuckle_charged_level_1",
      "category": "normal",
      "nameEN": "Psycho Knuckle (Charged Level 1)",
      "nameCN": "サイコナックル（ホールド Lv1）",
      "input": "5[hp]",
      "inputDisplay": "",
      "hitType": "High",
      "startup": "39",
      "active": "15",
      "recovery": "35",
      "onBlock": "-2",
      "onHit": "-",
      "damage": "800",
      "superArt": "1000",
      "driveOnHit": "3000",
      "driveOnBlock": "-6000",
      "driveOnPunishCounter": "-10000",
      "cancel": "-"
    },
    {
      "id": "psycho_knuckle_charged_level_2",
      "category": "normal",
      "nameEN": "Psycho Knuckle (Charged Level 2)",
      "nameCN": "サイコナックル（ホールド Lv2）",
      "input": "5[hp]",
      "inputDisplay": "",
      "hitType": "High",
      "startup": "69",
      "active": "15",
      "recovery": "35",
      "onBlock": "4",
      "onHit": "-",
      "damage": "1200",
      "superArt": "1200",
      "driveOnHit": "4000",
      "driveOnBlock": "-8000",
      "driveOnPunishCounter": "-12000",
      "cancel": "-"
    },
    {
      "id": "f_hp",
      "category": "normal",
      "nameEN": "Cobra Punch",
      "nameCN": "コブラパンチ",
      "input": "6hp",
      "inputDisplay": "",
      "hitType": "High",
      "startup": "17",
      "active": "3",
      "recovery": "21",
      "onBlock": "-3",
      "onHit": "1",
      "damage": "900",
      "superArt": "1000",
      "driveOnHit": "3000",
      "driveOnBlock": "-6000",
      "driveOnPunishCounter": "-10000",
      "cancel": "-"
    },
    {
      "id": "flicker_combination_2",
      "category": "targetcombo",
      "nameEN": "Flicker Combination (2)",
      "nameCN": "フリッカーコンビネーション（2段目）",
      "input": "5lk>5lk",
      "inputDisplay": "",
      "hitType": "High",
      "startup": "7",
      "active": "3",
      "recovery": "15",
      "onBlock": "-3",
      "onHit": "3",
      "damage": "400",
      "superArt": "400",
      "driveOnHit": "500",
      "driveOnBlock": "-1000",
      "driveOnPunishCounter": "-4000",
      "cancel": "-"
    },
    {
      "id": "flicker_combination_3",
      "category": "targetcombo",
      "nameEN": "Flicker Combination (3)",
      "nameCN": "フリッカーコンビネーション（3段目）",
      "input": "5lk>5lk>5lk",
      "inputDisplay": "",
      "hitType": "High",
      "startup": "7",
      "active": "3",
      "recovery": "16",
      "onBlock": "-8",
      "onHit": "1",
      "damage": "600",
      "superArt": "400",
      "driveOnHit": "500",
      "driveOnBlock": "-1500",
      "driveOnPunishCounter": "-4000",
      "cancel": "-"
    },
    {
      "id": "body_blow_combination",
      "category": "targetcombo",
      "nameEN": "Body Blow Combination",
      "nameCN": "ボディブローコンビネーション",
      "input": "5mp>5hp",
      "inputDisplay": "",
      "hitType": "High",
      "startup": "13",
      "active": "2",
      "recovery": "23",
      "onBlock": "-8",
      "onHit": "-",
      "damage": "400",
      "superArt": "400",
      "driveOnHit": "1000",
      "driveOnBlock": "-1000",
      "driveOnPunishCounter": "-4000",
      "cancel": "Other (kill-rush-backward)"
    },
    {
      "id": "hitman_combination_2",
      "category": "targetcombo",
      "nameEN": "Hitman Combination (2)",
      "nameCN": "ヒットマンコンビネーション（2段目）",
      "input": "5mk>5mk",
      "inputDisplay": "",
      "hitType": "High",
      "startup": "7",
      "active": "2",
      "recovery": "20",
      "onBlock": "-6",
      "onHit": "0",
      "damage": "300",
      "superArt": "400",
      "driveOnHit": "1500",
      "driveOnBlock": "-1000",
      "driveOnPunishCounter": "-4000",
      "cancel": "-"
    },
    {
      "id": "hitman_combination_3",
      "category": "targetcombo",
      "nameEN": "Hitman Combination (3)",
      "nameCN": "ヒットマンコンビネーション（3段目）",
      "input": "5mk>5mk>5hp",
      "inputDisplay": "",
      "hitType": "High",
      "startup": "11",
      "active": "5",
      "recovery": "23",
      "onBlock": "-11",
      "onHit": "-",
      "damage": "600",
      "superArt": "500",
      "driveOnHit": "1500",
      "driveOnBlock": "-2000",
      "driveOnPunishCounter": "-4000",
      "cancel": "-"
    },
    {
      "id": "low_smash_combination",
      "category": "targetcombo",
      "nameEN": "Low Smash Combination",
      "nameCN": "ロースマッシュコンビネーション",
      "input": "2hk>5hp",
      "inputDisplay": "",
      "hitType": "High",
      "startup": "12",
      "active": "5",
      "recovery": "19",
      "onBlock": "-8",
      "onHit": "-",
      "damage": "700",
      "superArt": "1200",
      "driveOnHit": "3500",
      "driveOnBlock": "-3000",
      "driveOnPunishCounter": "-4000",
      "cancel": "Super"
    },
    {
      "id": "psycho_spark",
      "category": "special",
      "nameEN": "Psycho Spark",
      "nameCN": "サイコスパーク",
      "input": "236*p",
      "inputDisplay": "",
      "hitType": "High",
      "startup": "14",
      "active": "12",
      "recovery": "8",
      "onBlock": "-5",
      "onHit": "3",
      "damage": "400",
      "superArt": "300",
      "driveOnHit": "1000",
      "driveOnBlock": "-2500",
      "driveOnPunishCounter": "-3000",
      "cancel": "Super"
    },
    {
      "id": "psycho_spark_od",
      "category": "special",
      "nameEN": "Psycho Spark (OD)",
      "nameCN": "サイコスパーク（OD）",
      "input": "236(pp)",
      "inputDisplay": "",
      "hitType": "High",
      "startup": "14",
      "active": "12",
      "recovery": "7",
      "onBlock": "-2",
      "onHit": "-",
      "damage": "400",
      "superArt": "400",
      "driveOnHit": "-",
      "driveOnBlock": "-2000",
      "driveOnPunishCounter": "-3000",
      "cancel": "Super"
    },
    {
      "id": "f_lp",
      "category": "special",
      "nameEN": "Psycho Shoot (Light)",
      "nameCN": "サイコシュート（弱）",
      "input": "6lp",
      "inputDisplay": "236*p>6lp",
      "hitType": "High",
      "startup": "12",
      "active": "-",
      "recovery": "-",
      "onBlock": "-8",
      "onHit": "3",
      "damage": "600",
      "superArt": "600",
      "driveOnHit": "1000",
      "driveOnBlock": "-2500",
      "driveOnPunishCounter": "-3000",
      "cancel": "Super"
    },
    {
      "id": "f_mp",
      "category": "special",
      "nameEN": "Psycho Shoot (Medium)",
      "nameCN": "サイコシュート（中）",
      "input": "6mp",
      "inputDisplay": "236*p>6mp",
      "hitType": "High",
      "startup": "12",
      "active": "-",
      "recovery": "-",
      "onBlock": "-8",
      "onHit": "3",
      "damage": "600",
      "superArt": "600",
      "driveOnHit": "1000",
      "driveOnBlock": "-2500",
      "driveOnPunishCounter": "-3000",
      "cancel": "Super"
    },
    {
      "id": "f_hp",
      "category": "special",
      "nameEN": "Psycho Shoot (Heavy)",
      "nameCN": "サイコシュート（強）",
      "input": "6hp",
      "inputDisplay": "236*p>6hp",
      "hitType": "High",
      "startup": "12",
      "active": "-",
      "recovery": "-",
      "onBlock": "-8",
      "onHit": "3",
      "damage": "600",
      "superArt": "600",
      "driveOnHit": "1000",
      "driveOnBlock": "-2500",
      "driveOnPunishCounter": "-3000",
      "cancel": "Super"
    },
    {
      "id": "f_lp",
      "category": "special",
      "nameEN": "Psycho Shoot (OD Light)",
      "nameCN": "サイコシュート（OD 弱）",
      "input": "6lp",
      "inputDisplay": "236(pp)>6lp",
      "hitType": "High",
      "startup": "12",
      "active": "-",
      "recovery": "-",
      "onBlock": "-2",
      "onHit": "-",
      "damage": "800",
      "superArt": "600",
      "driveOnHit": "-",
      "driveOnBlock": "-2500",
      "driveOnPunishCounter": "-5000",
      "cancel": "Super"
    },
    {
      "id": "f_mp",
      "category": "special",
      "nameEN": "Psycho Shoot (OD Medium)",
      "nameCN": "サイコシュート（OD 中）",
      "input": "6mp",
      "inputDisplay": "236(pp)>6mp",
      "hitType": "High",
      "startup": "12",
      "active": "-",
      "recovery": "-",
      "onBlock": "-2",
      "onHit": "-",
      "damage": "800",
      "superArt": "600",
      "driveOnHit": "-",
      "driveOnBlock": "-2500",
      "driveOnPunishCounter": "-5000",
      "cancel": "Super"
    },
    {
      "id": "f_hp",
      "category": "special",
      "nameEN": "Psycho Shoot (OD Heavy)",
      "nameCN": "サイコシュート（OD 強）",
      "input": "6hp",
      "inputDisplay": "236(pp)>6hp",
      "hitType": "High",
      "startup": "12",
      "active": "-",
      "recovery": "-",
      "onBlock": "-2",
      "onHit": "-",
      "damage": "800",
      "superArt": "600",
      "driveOnHit": "-",
      "driveOnBlock": "-2500",
      "driveOnPunishCounter": "-5000",
      "cancel": "Super"
    },
    {
      "id": "psycho_uppercut_light",
      "category": "special",
      "nameEN": "Psycho Uppercut (Light)",
      "nameCN": "サイコアッパー（弱）",
      "input": "623lp",
      "inputDisplay": "",
      "hitType": "High",
      "startup": "10",
      "active": "8",
      "recovery": "28",
      "onBlock": "-13",
      "onHit": "-",
      "damage": "900",
      "superArt": "800",
      "driveOnHit": "2000",
      "driveOnBlock": "-4000",
      "driveOnPunishCounter": "-5000",
      "cancel": "Super"
    },
    {
      "id": "psycho_uppercut_medium",
      "category": "special",
      "nameEN": "Psycho Uppercut (Medium)",
      "nameCN": "サイコアッパー（中）",
      "input": "623mp",
      "inputDisplay": "",
      "hitType": "High",
      "startup": "14",
      "active": "6",
      "recovery": "32",
      "onBlock": "-20",
      "onHit": "-",
      "damage": "1000",
      "superArt": "1200",
      "driveOnHit": "3000",
      "driveOnBlock": "-4000",
      "driveOnPunishCounter": "-5000",
      "cancel": "Super"
    },
    {
      "id": "psycho_uppercut_heavy",
      "category": "special",
      "nameEN": "Psycho Uppercut (Heavy)",
      "nameCN": "サイコアッパー（強）",
      "input": "623hp",
      "inputDisplay": "",
      "hitType": "High",
      "startup": "16",
      "active": "6",
      "recovery": "33",
      "onBlock": "-21",
      "onHit": "-",
      "damage": "1200",
      "superArt": "1500",
      "driveOnHit": "4000",
      "driveOnBlock": "-4000",
      "driveOnPunishCounter": "-5000",
      "cancel": "Super"
    },
    {
      "id": "psycho_uppercut_od",
      "category": "special",
      "nameEN": "Psycho Uppercut (OD)",
      "nameCN": "サイコアッパー（OD）",
      "input": "623(pp)",
      "inputDisplay": "",
      "hitType": "High",
      "startup": "13",
      "active": "6",
      "recovery": "36",
      "onBlock": "-28",
      "onHit": "-",
      "damage": "1600",
      "superArt": "1500",
      "driveOnHit": "-",
      "driveOnBlock": "-4000",
      "driveOnPunishCounter": "-",
      "cancel": "-"
    },
    {
      "id": "psycho_blitz_light",
      "category": "special",
      "nameEN": "Psycho Blitz (Light)",
      "nameCN": "サイコブリッツ（弱）",
      "input": "214lp",
      "inputDisplay": "",
      "hitType": "High",
      "startup": "11",
      "active": "3, 3, 4",
      "recovery": "14",
      "onBlock": "-5",
      "onHit": "3",
      "damage": "800",
      "superArt": "900",
      "driveOnHit": "2000",
      "driveOnBlock": "-3000",
      "driveOnPunishCounter": "-5000",
      "cancel": "Super"
    },
    {
      "id": "psycho_blitz_medium",
      "category": "special",
      "nameEN": "Psycho Blitz (Medium)",
      "nameCN": "サイコブリッツ（中）",
      "input": "214mp",
      "inputDisplay": "",
      "hitType": "High",
      "startup": "13",
      "active": "2, 3, 3",
      "recovery": "16",
      "onBlock": "-12",
      "onHit": "-",
      "damage": "900",
      "superArt": "1000",
      "driveOnHit": "2000",
      "driveOnBlock": "-3000",
      "driveOnPunishCounter": "-5000",
      "cancel": "Super"
    },
    {
      "id": "psycho_blitz_heavy",
      "category": "special",
      "nameEN": "Psycho Blitz (Heavy)",
      "nameCN": "サイコブリッツ（強）",
      "input": "214hp",
      "inputDisplay": "",
      "hitType": "High",
      "startup": "15",
      "active": "2, 2, 2",
      "recovery": "23",
      "onBlock": "-12",
      "onHit": "-",
      "damage": "1100",
      "superArt": "1100",
      "driveOnHit": "2000",
      "driveOnBlock": "-3000",
      "driveOnPunishCounter": "-5000",
      "cancel": "Super"
    },
    {
      "id": "psycho_blitz_od",
      "category": "special",
      "nameEN": "Psycho Blitz (OD)",
      "nameCN": "サイコブリッツ（OD）",
      "input": "214(pp)",
      "inputDisplay": "",
      "hitType": "High",
      "startup": "13",
      "active": "1, 1, 1, 1, 1, 1, 2",
      "recovery": "20",
      "onBlock": "-3",
      "onHit": "-",
      "damage": "1400",
      "superArt": "1200",
      "driveOnHit": "-",
      "driveOnBlock": "-4000",
      "driveOnPunishCounter": "-5000",
      "cancel": "Super"
    },
    {
      "id": "psycho_flicker_light",
      "category": "special",
      "nameEN": "Psycho Flicker (Light)",
      "nameCN": "サイコフリッカー（弱）",
      "input": "236lk",
      "inputDisplay": "",
      "hitType": "High",
      "startup": "16",
      "active": "4",
      "recovery": "26",
      "onBlock": "-6",
      "onHit": "1",
      "damage": "800",
      "superArt": "600",
      "driveOnHit": "2000",
      "driveOnBlock": "-2500",
      "driveOnPunishCounter": "-8000",
      "cancel": "Super"
    },
    {
      "id": "psycho_flicker_light_charged",
      "category": "special",
      "nameEN": "Psycho Flicker (Light Charged)",
      "nameCN": "サイコフリッカー（弱 ホールド）",
      "input": "236[lk]",
      "inputDisplay": "",
      "hitType": "High",
      "startup": "31",
      "active": "5",
      "recovery": "24",
      "onBlock": "4",
      "onHit": "-",
      "damage": "1000",
      "superArt": "800",
      "driveOnHit": "2000",
      "driveOnBlock": "-3000",
      "driveOnPunishCounter": "-5000",
      "cancel": "-"
    },
    {
      "id": "psycho_flicker_medium",
      "category": "special",
      "nameEN": "Psycho Flicker (Medium)",
      "nameCN": "サイコフリッカー（中）",
      "input": "236mk",
      "inputDisplay": "",
      "hitType": "High",
      "startup": "20",
      "active": "4",
      "recovery": "26",
      "onBlock": "-6",
      "onHit": "3",
      "damage": "900",
      "superArt": "600",
      "driveOnHit": "2000",
      "driveOnBlock": "-3000",
      "driveOnPunishCounter": "-10000",
      "cancel": "Super"
    },
    {
      "id": "psycho_flicker_medium_charged",
      "category": "special",
      "nameEN": "Psycho Flicker (Medium Charged)",
      "nameCN": "サイコフリッカー（中 ホールド）",
      "input": "236[mk]",
      "inputDisplay": "",
      "hitType": "High",
      "startup": "35",
      "active": "5",
      "recovery": "24",
      "onBlock": "4",
      "onHit": "-",
      "damage": "1000",
      "superArt": "800",
      "driveOnHit": "2000",
      "driveOnBlock": "-3000",
      "driveOnPunishCounter": "-5000",
      "cancel": "-"
    },
    {
      "id": "psycho_flicker_heavy",
      "category": "special",
      "nameEN": "Psycho Flicker (Heavy)",
      "nameCN": "サイコフリッカー（強）",
      "input": "236hk",
      "inputDisplay": "",
      "hitType": "High",
      "startup": "17",
      "active": "8",
      "recovery": "18",
      "onBlock": "-",
      "onHit": "-",
      "damage": "800",
      "superArt": "600",
      "driveOnHit": "2000",
      "driveOnBlock": "-",
      "driveOnPunishCounter": "-10000",
      "cancel": "Super"
    },
    {
      "id": "psycho_flicker_heavy_charged",
      "category": "special",
      "nameEN": "Psycho Flicker (Heavy Charged)",
      "nameCN": "サイコフリッカー（強 ホールド）",
      "input": "236[hk]",
      "inputDisplay": "",
      "hitType": "High",
      "startup": "35",
      "active": "10",
      "recovery": "19",
      "onBlock": "-",
      "onHit": "-",
      "damage": "1000",
      "superArt": "800",
      "driveOnHit": "3000",
      "driveOnBlock": "-",
      "driveOnPunishCounter": "-5000",
      "cancel": "-"
    },
    {
      "id": "psycho_flicker_od",
      "category": "special",
      "nameEN": "Psycho Flicker (OD)",
      "nameCN": "サイコフリッカー（OD）",
      "input": "236(kk)",
      "inputDisplay": "",
      "hitType": "High",
      "startup": "25",
      "active": "4",
      "recovery": "32",
      "onBlock": "4",
      "onHit": "-",
      "damage": "800",
      "superArt": "700",
      "driveOnHit": "-",
      "driveOnBlock": "-3000",
      "driveOnPunishCounter": "-5000",
      "cancel": "Super"
    },
    {
      "id": "kill_rush_forward",
      "category": "normal",
      "nameEN": "Kill Rush (Forward)",
      "nameCN": "キルステップ（前方）",
      "input": "5(kk)",
      "inputDisplay": "",
      "hitType": "-",
      "startup": "-",
      "active": "-",
      "recovery": "-",
      "onBlock": "-",
      "onHit": "-",
      "damage": "-",
      "superArt": "-",
      "driveOnHit": "-",
      "driveOnBlock": "-",
      "driveOnPunishCounter": "-",
      "cancel": "-"
    },
    {
      "id": "kill_switch_break",
      "category": "special",
      "nameEN": "Kill Switch Break",
      "nameCN": "キルスイッチ・ブレイク",
      "input": "6*p",
      "inputDisplay": "5(kk)>6*p",
      "hitType": "High",
      "startup": "11",
      "active": "3",
      "recovery": "20",
      "onBlock": "-4",
      "onHit": "-",
      "damage": "800",
      "superArt": "600",
      "driveOnHit": "2000",
      "driveOnBlock": "-5000",
      "driveOnPunishCounter": "-8000",
      "cancel": "Super"
    },
    {
      "id": "kill_switch_chaser",
      "category": "special",
      "nameEN": "Kill Switch Chaser",
      "nameCN": "キルスイッチ・チェイス",
      "input": "6*p",
      "inputDisplay": "5(kk)>6*p",
      "hitType": "High",
      "startup": "11",
      "active": "3",
      "recovery": "20",
      "onBlock": "-6",
      "onHit": "-",
      "damage": "600",
      "superArt": "600",
      "driveOnHit": "2000",
      "driveOnBlock": "-5000",
      "driveOnPunishCounter": "-8000",
      "cancel": "Super"
    },
    {
      "id": "kill_rush_backward",
      "category": "normal",
      "nameEN": "Kill Rush (Backward)",
      "nameCN": "キルステップ（後方）",
      "input": "4(kk)",
      "inputDisplay": "",
      "hitType": "-",
      "startup": "-",
      "active": "-",
      "recovery": "-",
      "onBlock": "-",
      "onHit": "-",
      "damage": "-",
      "superArt": "-",
      "driveOnHit": "-",
      "driveOnBlock": "-",
      "driveOnPunishCounter": "-",
      "cancel": "-"
    },
    {
      "id": "psycho_storm",
      "category": "super",
      "nameEN": "Psycho Storm",
      "nameCN": "サイコストーム",
      "input": "236236*k",
      "inputDisplay": "",
      "hitType": "High",
      "startup": "13",
      "active": "2, 2, 2, 2, 1, 1, 1",
      "recovery": "56",
      "onBlock": "-32",
      "onHit": "-",
      "damage": "2000",
      "superArt": "-",
      "driveOnHit": "-",
      "driveOnBlock": "-2500",
      "driveOnPunishCounter": "-5000",
      "cancel": "-"
    },
    {
      "id": "psycho_cannon",
      "category": "super",
      "nameEN": "Psycho Cannon",
      "nameCN": "サイコキャノン",
      "input": "214214*p",
      "inputDisplay": "",
      "hitType": "High",
      "startup": "8",
      "active": "-",
      "recovery": "-",
      "onBlock": "65",
      "onHit": "-",
      "damage": "1100",
      "superArt": "-",
      "driveOnHit": "-",
      "driveOnBlock": "-5000",
      "driveOnPunishCounter": "-10000",
      "cancel": "-"
    },
    {
      "id": "psycho_chamber",
      "category": "super",
      "nameEN": "Psycho Chamber",
      "nameCN": "サイコチェンバー",
      "input": "236236*p",
      "inputDisplay": "",
      "hitType": "High",
      "startup": "10",
      "active": "10",
      "recovery": "64",
      "onBlock": "-49",
      "onHit": "-",
      "damage": "4000",
      "superArt": "-",
      "driveOnHit": "-",
      "driveOnBlock": "-7500",
      "driveOnPunishCounter": "-15000",
      "cancel": "-"
    },
    {
      "id": "psycho_chamber_critical_art",
      "category": "super",
      "nameEN": "Psycho Chamber (Critical Art)",
      "nameCN": "サイコチェンバー（CA）",
      "input": "236236*p",
      "inputDisplay": "",
      "hitType": "High",
      "startup": "10",
      "active": "10",
      "recovery": "64",
      "onBlock": "-49",
      "onHit": "-",
      "damage": "4500",
      "superArt": "-",
      "driveOnHit": "-",
      "driveOnBlock": "-10000",
      "driveOnPunishCounter": "-20000",
      "cancel": "-"
    },
    {
      "id": "face_buster",
      "category": "normal",
      "nameEN": "Face Buster",
      "nameCN": "フェイスバスター",
      "input": "(lplk)",
      "inputDisplay": "",
      "hitType": "Throw",
      "startup": "5",
      "active": "3",
      "recovery": "23",
      "onBlock": "-",
      "onHit": "-",
      "damage": "1200",
      "superArt": "2000",
      "driveOnHit": "2000",
      "driveOnBlock": "-",
      "driveOnPunishCounter": "-10000",
      "cancel": "-"
    },
    {
      "id": "rib_crusher",
      "category": "normal",
      "nameEN": "Rib Crusher",
      "nameCN": "リブクラッシャー",
      "input": "(4lplk)",
      "inputDisplay": "",
      "hitType": "Throw",
      "startup": "5",
      "active": "3",
      "recovery": "23",
      "onBlock": "-",
      "onHit": "-",
      "damage": "1200",
      "superArt": "2000",
      "driveOnHit": "2000",
      "driveOnBlock": "-",
      "driveOnPunishCounter": "-10000",
      "cancel": "-"
    }
  ]
}